codetext/__init__.py
codetext/__main__.py
codetext/codetext_cli.py
codetext/clean/__init__.py
codetext/clean/noise_removal.py
codetext/parser/__init__.py
codetext/parser/c_sharp_parser.py
codetext/parser/cpp_parser.py
codetext/parser/go_parser.py
codetext/parser/java_parser.py
codetext/parser/javascript_parser.py
codetext/parser/language_parser.py
codetext/parser/php_parser.py
codetext/parser/python_parser.py
codetext/parser/ruby_parser.py
codetext/parser/rust_parser.py
codetext/utils/__init__.py
codetext/utils/imports.py
codetext/utils/utils.py
codetext-0.0.9.dist-info/LICENSE
codetext-0.0.9.dist-info/METADATA
codetext-0.0.9.dist-info/WHEEL
codetext-0.0.9.dist-info/entry_points.txt
codetext-0.0.9.dist-info/top_level.txt
codetext-0.0.9.dist-info/RECORD
