Metadata-Version: 2.1
Name: codetext
Version: 0.0.9
Summary: Multilingual programming language parsers for the extract from raw source code into multiple levels of pair data
Author-email: Dung Manh Nguyen <dungnm.workspace@gmail.com>
Project-URL: Homepage, https://github.com/AI4Code-Research/CodeText-data
Project-URL: Bug Tracker, https://github.com/AI4Code-Research/CodeText-data/issues
Classifier: Programming Language :: Python :: 3
Classifier: License :: OSI Approved :: MIT License
Classifier: Operating System :: OS Independent
Requires-Python: >=3.6
License-File: LICENSE
Requires-Dist: tree-sitter >=0.20
Requires-Dist: Levenshtein >=0.20
Requires-Dist: langdetect >=1.0.0
Requires-Dist: bs4 >=0.0.1
Requires-Dist: tabulate >=0.9.0
